pyisaf/__init__.py
pyisaf/utils.py
pyisaf/validators.py
pyisaf/builder/__init__.py
pyisaf/builder/base.py
pyisaf/builder/v1_2.py
pyisaf/isaf_schema/__init__.py
pyisaf/isaf_schema/v1_2/__init__.py
pyisaf/isaf_schema/v1_2/const.py
pyisaf/isaf_schema/v1_2/types.py
pyisaf-0.1.8.dist-info/DESCRIPTION.rst
pyisaf-0.1.8.dist-info/METADATA
pyisaf-0.1.8.dist-info/RECORD
pyisaf-0.1.8.dist-info/WHEEL
pyisaf-0.1.8.dist-info/metadata.json
pyisaf-0.1.8.dist-info/top_level.txt
