Metadata-Version: 2.0
Name: pyisaf
Version: 0.1.8
Summary: Python library for i.SAF VAT report generation.
Home-page: https://github.com/versada/pyisaf
Author: Naglis Jonaitis
Author-email: naglis@versada.eu
License: BSD license
Keywords: pyisaf
Platform: UNKNOWN
Classifier: Development Status :: 4 - Beta
Classifier: Intended Audience :: Developers
Classifier: License :: OSI Approved :: BSD License
Classifier: Natural Language :: English
Classifier: Programming Language :: Python :: 2
Classifier: Programming Language :: Python :: 2.7
Classifier: Programming Language :: Python :: 3
Classifier: Programming Language :: Python :: 3.5
Classifier: Programming Language :: Python :: 3.6
Requires-Dist: schema (<0.7.0,>=0.6.5)
